README.md
setup.py
metric_eval/__init__.py
metric_eval/metric_eval.py
metric_eval.egg-info/PKG-INFO
metric_eval.egg-info/SOURCES.txt
metric_eval.egg-info/dependency_links.txt
metric_eval.egg-info/requires.txt
metric_eval.egg-info/top_level.txt