Metadata-Version: 2.1
Name: metric-eval
Version: 1.0.2
Summary: a python package for evaluating evaluation metrics 
Author: Ziang Xiao, Susu Zhang
Author-email: ziang.xiao@jhu.edu, szhan105@illinois.edu
Keywords: python,metrics,evaluation,measurement,natural language processing,natural language generation
Classifier: Development Status :: 4 - Beta
Classifier: Intended Audience :: Developers
Classifier: Programming Language :: Python :: 3
Classifier: Operating System :: Unix
Classifier: Operating System :: MacOS :: MacOS X
Classifier: Operating System :: Microsoft :: Windows
